Workbook

Sheet Instructions
A3: You hold the following positions;
A5: 1. €100mil cash. EUR/USD spot exchange rate is currently 1.18
A7: 2. Long shares of American tech company B
A8: Current share price | B8: 422
A9: Number of share | B9: 750000
A11: 3. Long call options on American tech company C
A12: Number of contracts | B12: 2500
A13: Strike price (K) | B13: 390
A14: Expiry (T) | B14: 46311
A15: Implied vol | B15: 0.3292
A16: Risk free rate | B16: 0.0371
A20: Step 1 - Calculate the FRTB sensitivities for this set of positions
A22: Step 2 - Calculate the FRTB charge for each of the relevant SBM component
A24: Step 3 - Calculate the total FRTB SBM charge
A28: Please use a Black-Sholes model to value the option position

Sheet Student's worksheet
A2: FRTB SA calculations | F2: Inputs
F3: 1. FX Position - EUR Cash
F4: EUR cash notional | G4: 100000000
A5: SBM calculation | F5: EUR/USD spot | G5: 1.18
A7: Step 1 - Weighted sensitivites calculations | F7: 2. Equity Shares - Company B
F8: Share price (S) | G8: =Instructions!B8 -> 422
A9: A. Delta | B9: Sensitivity | C9: Weights | D9: Weighted sensitivity | E9: Calculation method | F9: # shares | G9: =Instructions!B9 -> 750000
A10: CR | B10: 0 | D10: 0
A11: EQ | B11: =G9*G8+G19*G20*G28*G13 -> 3.9084561e+08 | C11: =G34 -> 0.5 | D11: =B11*C11 -> 1.954228e+08 | E11: EQ delta = #shares * BS delta + #contracts * shares/contract * vega_per_share * spot (delta + vega cross term on the option position). | F11: 3. Equity Options - Company B
A12: FX | B12: =G4*G5 -> 118000000 | C12: =G37 -> 0.10606602 | D12: =B12*C12 -> 12515790 | E12: FX delta on EUR cash notional converted to USD (EUR notional * EUR/USD spot). | F12: Today | G12: =DATE(2026,4,24) -> 46136
A13: GIRR | B13: 0 | D13: 0 | F13: Spot (S) | G13: =Instructions!B8 -> 422
A14: Total | B14: =SUM(B10:B13) -> 5.0884561e+08 | D14: =SUM(D10:D13) -> 2.0793859e+08 | E14: Sum of CR, EQ, FX, GIRR delta sensitivities. | F14: Strike (K) | G14: =Instructions!B13 -> 390
F15: Expiry | G15: =Instructions!B14 -> 46311
A16: B. Vega | B16: Sensitivity | D16: Weighted sensitivity | E16: Calculation method | F16: Time to expiry T (yrs) | G16: =(G15-G12)/365 -> 0.47945205
A17: EQ | B17: =G29*G17*G30 -> 8301418.1 | C17: =G35 -> 0.7778 | D17: =B17*C17 -> 6456843 | E17: EQ vega = BS vega per share * implied vol * total option shares. | F17: Implied vol (sigma) | G17: =Instructions!B15 -> 0.3292
A18: FX | B18: 0 | D18: 0 | F18: Risk free rate (r) | G18: =Instructions!B16 -> 0.0371
A19: CR | B19: 0 | D19: 0 | F19: # contracts | G19: =Instructions!B12 -> 2500
A20: Total | B20: =SUM(B17:B19) -> 8301418.1 | D20: =SUM(D17:D19) -> 6456843 | E20: Sum of EQ, FX, CR vega sensitivities. | F20: Shares per contract | G20: 100
A22: C. Curvature | B22: Upward shock scenario | D22: Downward shock scenario | E22: Calculation method | F22: Black-Scholes (Company B option)
A23: EQ | B23: =-((G9*G40+G19*G20*G42)-(G9*G13+G19*G20*G27)-C23*B11) -> -10635359 | C23: =G36 -> 0.5 | D23: =-((G9*G41+G19*G20*G43)-(G9*G13+G19*G20*G27)+C23*B11) -> -22398996 | E23: EQ curvature up = -[ V(S_up) - V(S) - RW * delta ], where V(S) is option MV + underlying equity exposure. | F23: d1 | G23: =(LN(G13/G14)+(G18+G17^2/2)*G16)/(G17*SQRT(G16)) -> 0.53796015
A24: FX | B24: 0 | D24: 0 | F24: d2 | G24: =G23-G17*SQRT(G16) -> 0.31001391
A25: CR | B25: 0 | D25: 0 | F25: N(d1) | G25: =_xlfn.NORM.S.DIST(G23,TRUE) -> 0.70469772
A26: Total | B26: =SUM(B23:B25) -> -10635359 | D26: =SUM(D23:D25) -> -22398996 | E26: Sum of EQ, FX, CR upward curvature shocks. | F26: N(d2) | G26: =_xlfn.NORM.S.DIST(G24,TRUE) -> 0.62172481
F27: Call price (per share) | G27: =G13*G25-G14*EXP(-G18*G16)*G26 -> 59.184652
F28: BS Delta (per share) | G28: =G25 -> 0.70469772
A29: Step 2 - Risk aggregation | F29: BS Vega (per share, per 1.00 sigma) | G29: =G13*_xlfn.NORM.S.DIST(G23,FALSE)*SQRT(G16) -> 100.86778
F30: Total option shares | G30: =G19*G20 -> 250000
A31: Total FX charge | B31: =ABS(D12)+ABS(D18)+MAX(B24,D24,0) -> 12515790 | E31: FX total = |weighted FX delta| + |weighted FX vega| + max(FX curvature up, down, 0). | F31: Option MV (USD) | G31: =G27*G30 -> 14796163
F33: Risk Weights (from Parameters)
A34: Total EQ charge | B34: =ABS(D11)+ABS(D17)+MAX(B23,D23,0) -> 2.0187965e+08 | E34: EQ total = |weighted EQ delta| + |weighted EQ vega| + max(EQ curvature up, down, 0). | F34: EQ delta RW (bucket 8, large cap, liquid, tech) | G34: =Parameters!K14 -> 0.5
F35: EQ vega RW (large cap & indices) | G35: =Parameters!D45 -> 0.7778
F36: EQ curvature RW | G36: =G34 -> 0.5
A37: Total SBM | B37: =B31+B34 -> 2.1439544e+08 | E37: Total SBM = sum of asset-class charges. | F37: FX delta RW (EUR/USD specified pair) | G37: =Parameters!C36 -> 0.10606602
F39: EQ Curvature Revaluation
F40: S up (S*(1+RW)) | G40: =G13*(1+G34) -> 633
F41: S down (S*(1-RW)) | G41: =G13*(1-G34) -> 211
F42: Call price at S up (per share) | G42: =G40*_xlfn.NORM.S.DIST((LN(G40/G14)+(G18+G17^2/2)*G16)/(G17*SQRT(G16)),TRUE)-G14*EXP(-G18*G16)*_xlfn.NORM.S.DIST((LN(G40/G14)+(G18+G17^2/2)*G16)/(G17*SQRT(G16))-G17*SQRT(G16),TRUE) -> 250.41731
F43: Call price at S down (per share) | G43: =G41*_xlfn.NORM.S.DIST((LN(G41/G14)+(G18+G17^2/2)*G16)/(G17*SQRT(G16)),TRUE)-G14*EXP(-G18*G16)*_xlfn.NORM.S.DIST((LN(G41/G14)+(G18+G17^2/2)*G16)/(G17*SQRT(G16))-G17*SQRT(G16),TRUE) -> 0.089417881

Sheet Parameters
A2: I | B2: Delta parameters
B4: CSR | G4: EQ
M5: FX
B6: Bucket number | C6: Credit quality | D6: Sector | E6: Risk weight | G6: Bucket number | H6: Market cap | I6: Economy | J6: Sector | K6: Risk weight for spot price
B7: 1 | C7: IG | D7: Sovereign exposures, MDBs, and specified supranational entities | E7: 0.005 | G7: 1 | H7: Large market cap | I7: Emerging market economy | J7: Consumer goods and services, transportation and storage, administrative and support service activities, healthcare, and utilities | K7: 0.55 | N7: All currency pairs
B8: 2 | D8: PSEs, government-backed non- financials, GSE debt, education, and public administration | E8: 0.01 | G8: 2 | J8: Telecommunications and industrials | K8: 0.6 | N8: except for any currency pair formed by the following list of currencies, a [BANKING ORGANIZATION] may divide the above risk weight by the √2: United States Dollar, Australian Dollar, Brazilian Real, Canadian Dollar, Chinese Yuan, Euro, Hong Kong Dollar, Indian Rupee, Japanese Yen, Mexican Peso, New Zealand Dollar, Norwegian Krone, Singapore Dollar, South African Rand, South Korean Won, Swedish Krona, Swiss Franc, Turkish Lira, United Kingdom Pound, and any additional currencies specified
B9: 3 | D9: Financials including government-backed financials and real estate activities | E9: 0.05 | G9: 3 | J9: Basic materials, energy, agriculture, manufacturing, and mining and quarrying | K9: 0.45
B10: 4 | D10: Basic materials, energy, industrials, agriculture, manufacturing, and mining and quarrying | E10: 0.03 | G10: 4 | J10: Financials including government- backed financials, real estate activities, and technology | K10: 0.55
B11: 5 | D11: Consumer goods and services, transportation and storage, and administrative and support service activities | E11: 0.03 | G11: 5 | I11: Liquid market economy | J11: Consumer goods and services, transportation and storage, administrative and support service activities, healthcare, and utilities | K11: 0.3
B12: 6 | D12: Technology and telecommunications | E12: 0.02 | G12: 6 | J12: Telecommunications and industrials | K12: 0.35
B13: 7 | D13: Health care, utilities, and professional and technical activities | E13: 0.015 | G13: 7 | J13: Basic materials, energy, agriculture, manufacturing, and mining and quarrying | K13: 0.4
B14: 8 | D14: Covered bonds | E14: 0.015 | G14: 8 | J14: Financials including government- backed financials, real estate activities, and technology | K14: 0.5
B18: GIRR
F19: Correlation | H19: Interest Rate Risk Correlation Parameter (𝝆𝒌) within the Same bucket, with different tenors and the same IR curve Bucket, with Different Tenors and the Same Interest Rate Curve
B20: Tenor | C20: Risk weight | D20: USD Risk weight
B21: 0.25Y | C21: 0.017 | D21: =C21/SQRT(2) -> 0.012020815 | G21: 0.25Y | H21: 0.5Y | I21: 1Y | J21: 2Y | K21: 3Y | L21: 5Y | M21: 10Y | N21: 15Y | O21: 20Y | P21: 30Y
B22: 0.5Y | C22: 0.017 | D22: =C22/SQRT(2) -> 0.012020815 | F22: 0.25Y | G22: 1 | H22: 0.97 | I22: 0.914 | J22: 0.811 | K22: 0.719 | L22: 0.566 | M22: 0.4 | N22: 0.4 | O22: 0.4 | P22: 0.4
B23: 1Y | C23: 0.016 | D23: =C23/SQRT(2) -> 0.011313708 | F23: 0.5Y | H23: 1 | I23: 0.97 | J23: 0.914 | K23: 0.861 | L23: 0.763 | M23: 0.566 | N23: 0.419 | O23: 0.4 | P23: 0.4
B24: 2Y | C24: 0.013 | D24: =C24/SQRT(2) -> 0.0091923882 | F24: 1Y | I24: 1 | J24: 0.97 | K24: 0.942 | L24: 0.887 | M24: 0.763 | N24: 0.657 | O24: 0.566 | P24: 0.419
B25: 3Y | C25: 0.012 | D25: =C25/SQRT(2) -> 0.0084852814 | F25: 2Y | J25: 1 | K25: 0.985 | L25: 0.956 | M25: 0.887 | N25: 0.823 | O25: 0.763 | P25: 0.657
B26: 5Y | C26: 0.011 | D26: =C26/SQRT(2) -> 0.0077781746 | F26: 3Y | K26: 1 | L26: 0.98 | M26: 0.932 | N26: 0.887 | O26: 0.844 | P26: 0.763
B27: 10Y | C27: 0.011 | D27: =C27/SQRT(2) -> 0.0077781746 | F27: 5Y | L27: 1 | M27: 0.97 | N27: 0.942 | O27: 0.914 | P27: 0.861
B28: 15Y | C28: 0.011 | D28: =C28/SQRT(2) -> 0.0077781746 | F28: 10Y | M28: 1 | N28: 0.985 | O28: 0.97 | P28: 0.942
B29: 20Y | C29: 0.011 | D29: =C29/SQRT(2) -> 0.0077781746 | F29: 15Y | N29: 1 | O29: 0.99 | P29: 0.97
B30: 30Y | C30: 0.011 | D30: =C30/SQRT(2) -> 0.0077781746 | F30: 20Y | O30: 1 | P30: 0.985
D31: For United States Dollar, Australian Dollar, Canadian Dollar, Euro, Japanese Yen, Swedish Krona, and United Kingdom Pound, and any other currencies specified by the [AGENCY], a [BANKING ORGANIZATION] may divide the risk weights in paragraphs (b)(1)(ii) and (iii) of this section by √2. | F31: 30Y | P31: 1
B34: FX | C34: Risk weight
C35: 0.15 | D35: All currencies
C36: =C35/SQRT(2) -> 0.10606602 | D36: except for any currency pair formed by the following list of currencies, a [BANKING ORGANIZATION] may divide the above risk weight by the √2: United States Dollar, Australian Dollar, Brazilian Real, Canadian Dollar, Chinese Yuan, Euro, Hong Kong Dollar, Indian Rupee, Japanese Yen, Mexican Peso, New Zealand Dollar, Norwegian Krone, Singapore Dollar, South African Rand, South Korean Won, Swedish Krona, Swiss Franc, Turkish Lira, United Kingdom Pound, and any additional currencies specified
A38: I | B38: Vega parameters
C40: Risk Class | D40: Risk weights
B41: 1 | C41: Interest Rate Risk | D41: 1
B42: 2 | C42: Credit Spread Risk for non securitization | D42: 1
B43: 3 | C43: Credit Spread Risk for Correlation Trading Positions | D43: 1
B44: 4 | C44: Credit Spread Risk for securitization non-CTP | D44: 1
B45: 5 | C45: Equity Risk (large market cap and indices) | D45: 0.7778
B46: 6 | C46: Equity Risk (small market cap and other sector) | D46: 1
B47: 7 | C47: Commodity Risk | D47: 1
B48: 8 | C48: Foreign exchange risk | D48: 1
